compdata/__init__.py
compdata/comp_data.py
compdata-0.0.1.dist-info/LICENSE.txt
compdata-0.0.1.dist-info/METADATA
compdata-0.0.1.dist-info/WHEEL
compdata-0.0.1.dist-info/top_level.txt
compdata-0.0.1.dist-info/RECORD
