Metadata-Version: 2.1
Name: compdata
Version: 0.0.1
Summary: The compdata package provides access to the
Home-page: https://github.com/julianmarx/compdata
Author: Julian Marx
Author-email: jhw.marx@gmail.com
License: UNKNOWN
Keywords: finance,stocks,comparables data
Platform: UNKNOWN
